{"id":"saveversion","name":"saveversion","status":"STOPPED","esperHAEnabled":false,"enableErrorHandler":true,"topologySupervisors":[],"versionNumber":0,"parentVersionNumber":0,"description":"hdfs","customJarName":"","originalCustomJarName":"","customFileNames":"","sessionId":"0EA92E37732D352CABCA1F61FEFA2541","isReplayAlter":false,"engine":"spark","scheduling":null,"config":{"batchDuration":"1000","yarnUser":"hdfs","logLevel":"TRACE","keyTabSelectOption":"specifyKeyTabFilePath","keyTabFilePath":"","downloadKeytabFileLocation":"","zkKeyTabFileLocation":"","executorCores":"2","executorMemory":"512","receiverRateLimiter":"none","receiverMaxRate":"","enableBackPressure":"","enableCheckPoint":"false","checkPointDirectory":"/","eventLogEnabled":"false","eventLogDirectory":"/","poolNname":"FIFO","deploymentMode":"yarn-cluster","driverCores":"1","driverPermGenSize":"512","driverMemory":"512","taskMaxFailures":"4","yarnAmCores":"1","yarnAmMemory":"512","dynamicAllocationEnabled":"false","initialExecutors":"0","maxExecutors":"-1","executorInstances":"1","yarnQueue":"default","connectionName":"","appCores":"2","engine":"spark","typeOfApplication":"structuredstreaming","autoInspection":false,"clouderaLineage":false,"isConnectionMissing":false,"isDirty":false},"channels":[{"coordinates":[10,10],"className":"com.streamanalytix.spark.ss.receiver.SparkSSReceiver","label":"HDFS","inputDStreamType":"na","emitStreamIds":[{"emitStreamId":"saxErrorStream","outputFields":["tracemessage","streamIds"],"applyFilter":false,"filterCriteria":[],"componentId":"deadLaterChannel"}],"appType":"structuredstreaming,ssbatch","messageTypeId":"tracemessage","name":"DFSReceiverChannel_10412","id":"DFSReceiver-batchchannel","schemaIdentifier":"com.streamanalytix.engine.core.scheme.util.DefaultSchemaIdentifier","outputDStreamType":"plain","config":{"datasetTransformer":"com.streamanalytix.bs.dataset.service.impl.DfsChannelDSTransformer","datasetSourceType":"HDFS","oldToNewColumnNameMapping":{},"datasetName":"","connectionId":"181e88d6-abfd-46ab-91dc-6be23a22624f","isBatchEnabled":"true","connectionName":"Default","incrementalOffset":{"hdfstValue":"","enableIncrementalRead":false},"hdfsPath":"/user/ponta/dedup1.csv","saveAsDataset":false,"channelPlugin":"com.streamanalytix.spark.ss.receiver.DFSSource","connectionConfig":{},"operatorType":"receiver","saxInspect":{"datasetIds":{"inputdatasetId":[],"outputdatasetId":["DFSReceiverChannel_10412"]},"referenceSchemaId":{"inputSchemaId":[],"outputSchemaId":["DFSReceiverChannel_10412"]},"rowCount":100,"triggerTime":"3 seconds","samplingMethod":"topN","typeOfSchemaDetection":"readFromSource","detectSchema":false,"header":true},"subsystemName":"saveversion","parentTag":"/","parserType":"DELIMITED","delimiter":",","connectionJson":{"fsURI":"hdfs://cohdp265.spsoft-sz.com:8020","username":"hdfs","haEnabled":false},"enableIncrementalRead":false,"sourceHeader":true,"expfldlst":"","mvelfnclist":[]},"type":"channel","messageTypes":["DFSReceiverChannel_10412"],"channelType":"single","configured":true,"groupings":[],"errorConfig":{"partitions":"","connectionName":"Default","connectionId":"d98eb7ce-610f-45f3-bc88-10ca83c0fe6e","componentType":"rabbitmq","errorLogTarget":"rabbitmq","replicationFactor":"","isErrorHandlingRequired":true},"datamodel":[]}],"processors":[],"templateName":"","structure":"pipeline","alert":{"added":[],"updated":[],"deleted":[]},"connections":["181e88d6-abfd-46ab-91dc-6be23a22624f"],"autoInspectSchema":{"DFSReceiverChannel_10412":[{"name":"Number","alias":"Number","dataType":"java.lang.Integer","dateFormat":"yyyy-MM-dd HH:mm:ss","inputDateFormat":"yyyy-MM-dd HH:mm:ss","outputDateFormat":"yyyy-MM-dd HH:mm:ss","stringToDate":false,"isInputField":"Y","isTimestampField":"N","selected":true},{"name":"Name","alias":"Name","dataType":"java.lang.String","dateFormat":"yyyy-MM-dd HH:mm:ss","inputDateFormat":"yyyy-MM-dd HH:mm:ss","outputDateFormat":"yyyy-MM-dd HH:mm:ss","stringToDate":false,"isInputField":"Y","isTimestampField":"N","selected":true},{"name":"City","alias":"City","dataType":"java.lang.String","dateFormat":"yyyy-MM-dd HH:mm:ss","inputDateFormat":"yyyy-MM-dd HH:mm:ss","outputDateFormat":"yyyy-MM-dd HH:mm:ss","stringToDate":false,"isInputField":"Y","isTimestampField":"N","selected":true},{"name":"State","alias":"State","dataType":"java.lang.String","dateFormat":"yyyy-MM-dd HH:mm:ss","inputDateFormat":"yyyy-MM-dd HH:mm:ss","outputDateFormat":"yyyy-MM-dd HH:mm:ss","stringToDate":false,"isInputField":"Y","isTimestampField":"N","selected":true}]},"displayColumnsMap":{"DFSReceiverChannel_10412":{"DFSReceiverChannel_10412":{"allCols":["Number","Name","City","State"],"displayCols":["Number","Name","City","State"],"types":{"Number":"java.lang.Integer","Name":"java.lang.String","City":"java.lang.String","State":"java.lang.String"},"uniqueValues":{"Number":5,"State":6,"City":5,"Name":4}}}},"customJarBeforeModification":"","subsystemName":"saveversion","tenantId":"2","tempPipelineName":"Pipeline_1593674099464"}